holonote/__init__.py
holonote/__version.py
holonote/_version.py
holonote/_warnings.py
holonote/annotate/__init__.py
holonote/annotate/annotator.py
holonote/annotate/connector.py
holonote/annotate/display.py
holonote/annotate/table.py
holonote/annotate/typing.py
holonote/app/__init__.py
holonote/app/panel.py
holonote/app/tabulator.py
holonote/editor/__init__.py
holonote/editor/editors.py
holonote/tests/conftest.py
holonote/tests/test_annotation_table.py
holonote/tests/test_annotators_advanced.py
holonote/tests/test_annotators_basic.py
holonote/tests/test_annotators_element.py
holonote/tests/test_annotators_interface.py
holonote/tests/test_annotators_style.py
holonote/tests/test_app.py
holonote/tests/test_connectors.py
holonote/tests/test_display.py
holonote/tests/util.py
holonote/tests/benchmark/test_benchmarks.py
holonote-0.2.1.dist-info/METADATA
holonote-0.2.1.dist-info/WHEEL
holonote-0.2.1.dist-info/licenses/LICENSE.txt
holonote-0.2.1.dist-info/RECORD
