Metadata-Version: 2.3
Name: holonote
Version: 0.2.1
Summary: Annotate your data
License: Copyright (c) 2023, HoloViz team (holoviz.org).
License-File: LICENSE.txt
Keywords: annotation,holoviews,tools
Classifier: Operating System :: OS Independent
Classifier: Programming Language :: Python :: 3.9
Classifier: Programming Language :: Python :: 3.10
Classifier: Programming Language :: Python :: 3.11
Classifier: Programming Language :: Python :: 3.12
Requires-Python: >=3.9
Requires-Dist: holoviews>=1.18.0
Requires-Dist: pandas
Provides-Extra: examples
Requires-Dist: dask[dataframe]; extra == 'examples'
Requires-Dist: datashader; extra == 'examples'
Requires-Dist: fastparquet; extra == 'examples'
Requires-Dist: hvplot; extra == 'examples'
Requires-Dist: jupyterlab; extra == 'examples'
Requires-Dist: jupyterlab-myst; extra == 'examples'
Requires-Dist: scipy; extra == 'examples'
Provides-Extra: recommended
Requires-Dist: dask[dataframe]; extra == 'recommended'
Requires-Dist: datashader; extra == 'recommended'
Requires-Dist: fastparquet; extra == 'recommended'
Requires-Dist: hvplot; extra == 'recommended'
Requires-Dist: scipy; extra == 'recommended'
Provides-Extra: tests
Requires-Dist: pytest; extra == 'tests'
